mlstudio/__init__.py
mlstudio/analysis/__init__.py
mlstudio/analysis/model_validation.py
mlstudio/analysis/diagnostics/__init__.py
mlstudio/analysis/diagnostics/optimization.py
mlstudio/demo/__init__.py
mlstudio/demo/data/__init__.py
mlstudio/demo/data/Ames/__init__.py
mlstudio/demo/data/Ames/test.csv
mlstudio/demo/data/Ames/train.csv
mlstudio/demo/figures/__init__.py
mlstudio/demo/gradient_descent/__init__.py
mlstudio/demo/gradient_descent/benchmark.py
mlstudio/demo/gradient_descent/variants.py
mlstudio/demo/gradient_descent/regression/__init__.py
mlstudio/demo/gradient_descent/regression/regression_animation.py
mlstudio/demo/gradient_descent/regression/regression_evaluation.py
mlstudio/supervised/__init__.py
mlstudio/supervised/core/__init__.py
mlstudio/supervised/core/activations.py
mlstudio/supervised/core/objectives.py
mlstudio/supervised/core/optimizers.py
mlstudio/supervised/core/regularizers.py
mlstudio/supervised/core/scorers.py
mlstudio/supervised/core/tasks.py
mlstudio/supervised/deep_learning/__init__.py
mlstudio/supervised/machine_learning/__init__.py
mlstudio/supervised/machine_learning/gradient_descent.py
mlstudio/supervised/machine_learning/linear_regression.py
mlstudio/supervised/machine_learning/ols_regression.py
mlstudio/supervised/observers/__init__.py
mlstudio/supervised/observers/base.py
mlstudio/supervised/observers/debugging.py
mlstudio/supervised/observers/early_stop.py
mlstudio/supervised/observers/history.py
mlstudio/supervised/observers/learning_rate.py
mlstudio/utils/__init__.py
mlstudio/utils/data_analyzer.py
mlstudio/utils/data_manager.py
mlstudio/utils/file_manager.py
mlstudio/utils/format.py
mlstudio/utils/print.py
mlstudio/utils/validation.py
mlstudio/visual/__init__.py
mlstudio/visual/animations.py
mlstudio/visual/base.py
mlstudio/visual/interactive.py
mlstudio/visual/model_evaluation.py
mlstudio/visual/model_selection.py
mlstudio/visual/model_validation.py
mlstudio/visual/plots.py
mlstudio/visual/text.py
MLStudio-0.1.15.dist-info/AUTHORS.rst
MLStudio-0.1.15.dist-info/LICENSE
MLStudio-0.1.15.dist-info/METADATA
MLStudio-0.1.15.dist-info/WHEEL
MLStudio-0.1.15.dist-info/top_level.txt
MLStudio-0.1.15.dist-info/RECORD
