Metadata-Version: 2.1
Name: MLStudio
Version: 0.1.15
Summary: Machine Learning Algorithms
Home-page: https://github.com/decisionscients/MLStudio
Author: John James
Author-email: jjames@decisionscients.com
License: BSD license
Keywords: MLStudio
Platform: UNKNOWN
Classifier: Development Status :: 2 - Pre-Alpha
Classifier: Intended Audience :: Developers
Classifier: License :: OSI Approved :: BSD License
Classifier: Natural Language :: English
Classifier: Programming Language :: Python :: 3
Classifier: Programming Language :: Python :: 3.5
Classifier: Programming Language :: Python :: 3.6
Classifier: Programming Language :: Python :: 3.7
Classifier: Programming Language :: Python :: 3.8
Requires-Python: >=3.5
